[
  {
    "dependsOn": [
      {
        "modId": "viverridae"
      }
    ],
    "file": "viverridae:entities/land/nandiniidae.json",
    "op": "replace",
    "path": "/server/behaviors/drops/0/quantityByType/*-adult-*-nandiniabinotata/avg",
    "value": 0.5
  },
  {
    "dependsOn": [
      {
        "modId": "viverridae"
      }
    ],
    "file": "viverridae:entities/land/nandiniidae.json",
    "op": "replace",
    "path": "/server/behaviors/drops/0/quantityByType/*-baby-*/var",
    "value": 0.1
  },
  {
    "dependsOn": [
      {
        "modId": "viverridae"
      }
    ],
    "file": "viverridae:entities/land/nandiniidae.json",
    "op": "replace",
    "path": "/server/behaviors/drops/1/quantityByType/*-adult-*/avg",
    "value": 1
  },
  {
    "dependsOn": [
      {
        "modId": "viverridae"
      }
    ],
    "file": "viverridae:entities/land/nandiniidae.json",
    "op": "replace",
    "path": "/server/behaviors/9/hoursToGrowByType/*",
    "value": 175
  },
  {
    "dependsOn": [
      {
        "modId": "viverridae"
      }
    ],
    "file": "viverridae:entities/land/nandiniidae.json",
    "op": "replace",
    "path": "/server/behaviors/9/hoursToGrowByType/*-nandiniabinotata",
    "value": 263
  },
  {
    "dependsOn": [
      {
        "modId": "viverridae"
      }
    ],
    "file": "viverridae:entities/land/nandiniidae.json",
    "op": "replace",
    "path": "/server/behaviors/8/multiplyCooldownDaysMaxByType/*",
    "value": 9
  },
  {
    "dependsOn": [
      {
        "modId": "viverridae"
      }
    ],
    "file": "viverridae:entities/land/nandiniidae.json",
    "op": "replace",
    "path": "/server/behaviors/8/multiplyCooldownDaysMinByType/*",
    "value": 5
  },
  {
    "dependsOn": [
      {
        "modId": "viverridae"
      }
    ],
    "file": "viverridae:entities/land/nandiniidae.json",
    "op": "replace",
    "path": "/server/behaviors/8/pregnancyDaysByType/*",
    "value": 14
  },
  {
    "dependsOn": [
      {
        "modId": "viverridae"
      }
    ],
    "file": "viverridae:entities/land/nandiniidae.json",
    "op": "replace",
    "path": "/server/behaviors/8/pregnancyDaysByType/*-nandiniabinotata",
    "value": 9
  },
  {
    "dependsOn": [
      {
        "modId": "viverridae"
      }
    ],
    "file": "viverridae:entities/land/viverridae.json",
    "op": "replace",
    "path": "/server/behaviors/drops/0/quantityByType/*-adult-*-arctictisbinturong/avg",
    "value": 1.5
  },
  {
    "dependsOn": [
      {
        "modId": "viverridae"
      }
    ],
    "file": "viverridae:entities/land/viverridae.json",
    "op": "replace",
    "path": "/server/behaviors/drops/0/quantityByType/*-adult-*-arctictisbinturong/var",
    "value": 0.5
  },
  {
    "dependsOn": [
      {
        "modId": "viverridae"
      }
    ],
    "file": "viverridae:entities/land/viverridae.json",
    "op": "replace",
    "path": "/server/behaviors/drops/0/quantityByType/*-adult-*-civettictiscivetta/avg",
    "value": 1.5
  },
  {
    "dependsOn": [
      {
        "modId": "viverridae"
      }
    ],
    "file": "viverridae:entities/land/viverridae.json",
    "op": "replace",
    "path": "/server/behaviors/drops/0/quantityByType/*-adult-*-civettictiscivetta/var",
    "value": 0.5
  },
  {
    "dependsOn": [
      {
        "modId": "viverridae"
      }
    ],
    "file": "viverridae:entities/land/viverridae.json",
    "op": "replace",
    "path": "/server/behaviors/drops/0/quantityByType/*-adult-*-macrogalidiamusschenbroekii/avg",
    "value": 1.5
  },
  {
    "dependsOn": [
      {
        "modId": "viverridae"
      }
    ],
    "file": "viverridae:entities/land/viverridae.json",
    "op": "replace",
    "path": "/server/behaviors/drops/0/quantityByType/*-adult-*-macrogalidiamusschenbroekii/var",
    "value": 0.5
  },
  {
    "dependsOn": [
      {
        "modId": "viverridae"
      }
    ],
    "file": "viverridae:entities/land/viverridae.json",
    "op": "replace",
    "path": "/server/behaviors/drops/0/quantityByType/*-adult-*-viverracivettina/avg",
    "value": 1.5
  },
  {
    "dependsOn": [
      {
        "modId": "viverridae"
      }
    ],
    "file": "viverridae:entities/land/viverridae.json",
    "op": "replace",
    "path": "/server/behaviors/drops/0/quantityByType/*-adult-*-viverracivettina/var",
    "value": 0.5
  },
  {
    "dependsOn": [
      {
        "modId": "viverridae"
      }
    ],
    "file": "viverridae:entities/land/viverridae.json",
    "op": "replace",
    "path": "/server/behaviors/drops/0/quantityByType/*-adult-*-viverramegaspila/avg",
    "value": 1.5
  },
  {
    "dependsOn": [
      {
        "modId": "viverridae"
      }
    ],
    "file": "viverridae:entities/land/viverridae.json",
    "op": "replace",
    "path": "/server/behaviors/drops/0/quantityByType/*-adult-*-viverramegaspila/var",
    "value": 0.5
  },
  {
    "dependsOn": [
      {
        "modId": "viverridae"
      }
    ],
    "file": "viverridae:entities/land/viverridae.json",
    "op": "replace",
    "path": "/server/behaviors/drops/0/quantityByType/*-adult-*-viverrazibetha/avg",
    "value": 1.5
  },
  {
    "dependsOn": [
      {
        "modId": "viverridae"
      }
    ],
    "file": "viverridae:entities/land/viverridae.json",
    "op": "replace",
    "path": "/server/behaviors/drops/0/quantityByType/*-adult-*-viverrazibetha/var",
    "value": 0.5
  },
  {
    "dependsOn": [
      {
        "modId": "viverridae"
      }
    ],
    "file": "viverridae:entities/land/viverridae.json",
    "op": "replace",
    "path": "/server/behaviors/drops/0/quantityByType/*-adult-*/avg",
    "value": 0.5
  },
  {
    "dependsOn": [
      {
        "modId": "viverridae"
      }
    ],
    "file": "viverridae:entities/land/viverridae.json",
    "op": "replace",
    "path": "/server/behaviors/drops/0/quantityByType/*-baby-*/var",
    "value": 0.1
  },
  {
    "dependsOn": [
      {
        "modId": "viverridae"
      }
    ],
    "file": "viverridae:entities/land/viverridae.json",
    "op": "replace",
    "path": "/server/behaviors/drops/1/quantityByType/*-adult-*/avg",
    "value": 1
  },
  {
    "dependsOn": [
      {
        "modId": "viverridae"
      }
    ],
    "file": "viverridae:entities/land/viverridae.json",
    "op": "replace",
    "path": "/server/behaviors/9/hoursToGrowByType/*",
    "value": 88
  },
  {
    "dependsOn": [
      {
        "modId": "viverridae"
      }
    ],
    "file": "viverridae:entities/land/viverridae.json",
    "op": "replace",
    "path": "/server/behaviors/8/multiplyCooldownDaysMaxByType/*",
    "value": 9
  },
  {
    "dependsOn": [
      {
        "modId": "viverridae"
      }
    ],
    "file": "viverridae:entities/land/viverridae.json",
    "op": "replace",
    "path": "/server/behaviors/8/multiplyCooldownDaysMinByType/*",
    "value": 5
  },
  {
    "dependsOn": [
      {
        "modId": "viverridae"
      }
    ],
    "file": "viverridae:entities/land/viverridae.json",
    "op": "replace",
    "path": "/server/behaviors/8/pregnancyDaysByType/*",
    "value": 7
  }
]
